data/multiview_mnist.hdf5
doc/conf.py
doc/index.rst
doc/reference/api.rst
doc/tutorial/credits.rst
doc/tutorial/estimator_template.rst
doc/tutorial/install_devel.rst
doc/tutorial/times.rst
doc/tutorial/auto_examples/index.rst
doc/tutorial/auto_examples/combo/plot_cumbo_2_views_2_classes.ipynb
doc/tutorial/auto_examples/combo/plot_cumbo_2_views_2_classes.py
doc/tutorial/auto_examples/combo/plot_cumbo_2_views_2_classes.py.md5
doc/tutorial/auto_examples/combo/plot_cumbo_2_views_2_classes.rst
doc/tutorial/auto_examples/combo/plot_cumbo_3_views_3_classes.ipynb
doc/tutorial/auto_examples/combo/plot_cumbo_3_views_3_classes.py
doc/tutorial/auto_examples/combo/plot_cumbo_3_views_3_classes.py.md5
doc/tutorial/auto_examples/combo/plot_cumbo_3_views_3_classes.rst
doc/tutorial/auto_examples/combo/sg_execution_times.rst
doc/tutorial/auto_examples/combo/images/sphx_glr_plot_cumbo_2_views_2_classes_001.png
doc/tutorial/auto_examples/combo/images/sphx_glr_plot_cumbo_3_views_3_classes_001.png
doc/tutorial/auto_examples/combo/images/thumb/sphx_glr_plot_cumbo_2_views_2_classes_thumb.png
doc/tutorial/auto_examples/combo/images/thumb/sphx_glr_plot_cumbo_3_views_3_classes_thumb.png
doc/tutorial/auto_examples/mumbo/plot_mumbo_2_views_2_classes.ipynb
doc/tutorial/auto_examples/mumbo/plot_mumbo_2_views_2_classes.py
doc/tutorial/auto_examples/mumbo/plot_mumbo_2_views_2_classes.py.md5
doc/tutorial/auto_examples/mumbo/plot_mumbo_2_views_2_classes.rst
doc/tutorial/auto_examples/mumbo/plot_mumbo_3_views_3_classes.ipynb
doc/tutorial/auto_examples/mumbo/plot_mumbo_3_views_3_classes.py
doc/tutorial/auto_examples/mumbo/plot_mumbo_3_views_3_classes.py.md5
doc/tutorial/auto_examples/mumbo/plot_mumbo_3_views_3_classes.rst
doc/tutorial/auto_examples/mumbo/sg_execution_times.rst
doc/tutorial/auto_examples/mumbo/images/sphx_glr_plot_mumbo_2_views_2_classes_001.png
doc/tutorial/auto_examples/mumbo/images/sphx_glr_plot_mumbo_2_views_2_classes_002.png
scikit_multimodallearn-0.1.0.dist-info/METADATA
scikit_multimodallearn-0.1.0.dist-info/WHEEL
scikit_multimodallearn-0.1.0.dist-info/top_level.txt
scikit_multimodallearn-0.1.0.dist-info/RECORD
