Metadata-Version: 2.4
Name: scikit-multimodallearn
Version: 0.1.0
Summary: A scikit-learn compatible package for multimodal Classifiers
Author: Sokol Koço, Florent Jaillet, Riikka Huusari, Cécile Capponi, Baptiste Bauvin, Hachem Kadri'
Author-email: Dominique Benielli <dominique.benielli@univ-amu.fr>
License: BSD-3-Clause
Project-URL: Sources, https://github.com/multi-learn/scikit-multimodallearn
Project-URL: Documentation, https://multi-learn.github.io/scikit-multimodallearn/
Project-URL: Bug Tracker, https://github.com/multi-learn/scikit-multimodallearn/issues
Keywords: machine learning, supervised learning, classification, ensemble methods, boosting, kernel
Classifier: Development Status :: 5 - Production/Stable
Classifier: Intended Audience :: Science/Research
Classifier: Programming Language :: Python :: 3
Classifier: Programming Language :: Python :: 3.6
Classifier: Programming Language :: Python :: 3.7
Classifier: Programming Language :: Python :: 3.8
Classifier: Programming Language :: Python :: 3.9
Classifier: Programming Language :: Python :: 3.10
Classifier: Programming Language :: Python :: 3.11
Classifier: Topic :: Scientific/Engineering
Classifier: Topic :: Scientific/Engineering :: Artificial Intelligence
Classifier: Operating System :: Microsoft :: Windows
Classifier: Operating System :: POSIX :: Linux
Classifier: Operating System :: MacOS :: MacOS X
Requires-Python: >=3.6
Requires-Dist: numpy>=1.24
Requires-Dist: scikit-learn>=1.2.1
Requires-Dist: scipy
Requires-Dist: cvxopt>=1.3.1
Requires-Dist: six
Provides-Extra: test
Requires-Dist: pytest; extra == "test"
Requires-Dist: coverage==4.5.3; extra == "test"
Requires-Dist: pytest-cov; extra == "test"
Provides-Extra: doc
Requires-Dist: sphinx==5.0; extra == "doc"
Requires-Dist: numpydoc; extra == "doc"
Requires-Dist: sphinx_gallery; extra == "doc"
Requires-Dist: matplotlib; extra == "doc"
Requires-Dist: sphinx_rtd_theme; extra == "doc"
Dynamic: license
